{
  "date": "2026-03-08",
  "displayDate": "MAR 8, 2026",
  "bottomWord": "EXPANSION",
  "stories": [
    {
      "id": 1,
      "headline": "We've been speaking to Iranians during one week of war. Here's what they said",
      "description": "Ordinary Iranians reflect on seven days of conflict and where they see their country going next.",
      "mainLocation": {
        "name": "TEHRAN, IRAN",
        "lat": 35.6892523,
        "lng": 51.3896004
      },
      "intensity": 45,
      "color": "#ff2d55",
      "url": "https://www.bbc.co.uk/news/articles/c5y5lqygrn7o",
      "imageUrl": "https://ichef.bbci.co.uk/ace/branded_news/1200/cpsprodpb/f6b0/live/5ec6cc60-1979-11f1-9156-4356592fc9c8.jpg"
    },
    {
      "id": 4,
      "headline": "Hezbollah, Israeli troops clash on the ground in eastern Lebanon’s Bekaa",
      "description": "Lebanese Health Ministry says at least 12 people killed, 33 wounded in Israeli air raids on the town of Nabi Chit.",
      "mainLocation": {
        "name": "NABI CHIT, LEBANON",
        "lat": 33.8886842,
        "lng": 36.1181097
      },
      "intensity": 72,
      "color": "#34c759",
      "url": "https://www.aljazeera.com/news/2026/3/7/hezbollah-israeli-troops-clash-on-the-ground-in-eastern-lebanons-bekaa",
      "imageUrl": "https://www.aljazeera.com/wp-content/uploads/2026/03/afp_69abc7a8b7be-1772865448.jpg?resize=1920%2C1440"
    },
    {
      "id": 8,
      "headline": "Iranian missiles intercepted over Saudi, Jordan, drones launched at Qatar",
      "description": "Qatar says it came under a wave of drone attacks, with 10 fired from Iran, nine intercepted.",
      "mainLocation": {
        "name": "DOHA, QATAR",
        "lat": 25.3108807,
        "lng": 51.5081812
      },
      "intensity": 75,
      "color": "#ffb800",
      "url": "https://www.aljazeera.com/news/2026/3/7/iranian-missiles-intercepted-over-saudi-jordan-drones-launched-at-qatar",
      "imageUrl": "https://www.aljazeera.com/wp-content/uploads/2026/03/2026-03-05T141329Z_1811170377_RC2EYJA6X3EH_RTRMADP_3_IRAN-CRISIS-SAUDI-1772846462.jpg?resize=1920%2C1440"
    },
    {
      "id": 11,
      "headline": "Oil and gas prices surge as Iran war expands",
      "description": "Oil prices surge past $90 after the U.S. and Israel attacked Iran, escalating Middle East war.",
      "mainLocation": {
        "name": "TEL AVIV, ISRAEL",
        "lat": 32.0852997,
        "lng": 34.7818064
      },
      "intensity": 85,
      "color": "#ff2d55",
      "url": "https://apnews.com/article/oil-gasoline-iran-war-inflation-1a1b7c3e5fbd735aa87c43ac664501cb",
      "imageUrl": "https://dims.apnews.com/dims4/default/4c4c48c/2147483647/strip/true/crop/2774x1848+0+1/resize/980x653!/quality/90/?url=https%3A%2F%2Fassets.apnews.com%2Fab%2F17%2F52150d8ae20bc7477b9f5a3d3aa1%2Fe51a389e09fa49dea82415c606be9f85"
    },
    {
      "id": 15,
      "headline": "Newspaper headlines: 'Trump demands Iran's surrender' and 'UK voters say no to joining war'",
      "description": "The conflict in the Middle East continues to lead today's papers as the US calls for Iran's \"unconditional surrender\".",
      "mainLocation": {
        "name": "LONDON, UK",
        "lat": 51.5074456,
        "lng": -0.1277653
      },
      "intensity": 75,
      "color": "#5ac8fa",
      "url": "https://www.bbc.co.uk/news/articles/cddnqp45rdqo",
      "imageUrl": "https://ichef.bbci.co.uk/ace/branded_news/1200/cpsprodpb/8b83/live/836b6fe0-19b4-11f1-b048-c9424b2cf5fd.jpg"
    }
  ]
}