{
  "date": "2026-05-24",
  "displayDate": "MAY 24, 2026",
  "bottomWord": "LEVERAGE",
  "stories": [
    {
      "id": 1,
      "headline": "Zelenskyy says ‘time is right’ for Ukraine to start process of joining EU",
      "description": "His comments come as both Kyiv and Moscow try to advance their interests on the battlefield.",
      "mainLocation": {
        "name": "KYIV, UKRAINE",
        "lat": 50.4500336,
        "lng": 30.5241361
      },
      "intensity": 65,
      "color": "#ff2d55",
      "url": "https://www.aljazeera.com/news/2026/5/23/zelenskyy-says-time-is-right-for-ukraine-to-start-process-of-joining-eu",
      "imageUrl": "https://www.aljazeera.com/wp-content/uploads/2024/12/AP24354510502872-1735579384.jpg?resize=1920%2C1440"
    },
    {
      "id": 2,
      "headline": "Israel attacks southern Lebanon and near Syrian border despite ‘ceasefire’",
      "description": "People in southern Lebanon are living under “psychological terror” from Israeli air attacks and displacement orders.",
      "mainLocation": {
        "name": "TEL AVIV, ISRAEL",
        "lat": 32.0852997,
        "lng": 34.7818064
      },
      "intensity": 65,
      "color": "#ff6b35",
      "url": "https://www.aljazeera.com/news/2026/5/23/israel-attacks-southern-lebanon-and-near-syrian-border-despite-ceasefire",
      "imageUrl": "https://www.aljazeera.com/wp-content/uploads/2026/05/AFP__20260523__B3TH8WE__v1__HighRes__LebanonIsraelIranUsWar-1779517052.jpg?resize=1920%2C1440"
    },
    {
      "id": 3,
      "headline": "Missiles to munitions: Does the US risk running out of key weapons?",
      "description": "The US projects confidence in weapons stockpiles, but analysts say dwindling munitions are shaping its war decisions.",
      "mainLocation": {
        "name": "WASHINGTON D.C., USA",
        "lat": 38.8950982,
        "lng": -77.0363849
      },
      "intensity": 65,
      "color": "#ffb800",
      "url": "https://www.aljazeera.com/features/2026/5/23/missiles-to-munitions-does-the-us-risk-running-out-of-key-weapons",
      "imageUrl": "https://www.aljazeera.com/wp-content/uploads/2026/05/2026-04-23T071710Z_787943666_RC2TUKAYHZCU_RTRMADP_3_IRAN-CRISIS-BRITAIN-1779455296.jpg?resize=1920%2C1440"
    },
    {
      "id": 6,
      "headline": "Iran weighs US peace proposal despite ‘deep and significant’ disagreements",
      "description": "A visit by Pakistan’s army chief to Tehran is seen as a sign of significant progress in negotiations.",
      "mainLocation": {
        "name": "TEHRAN, IRAN",
        "lat": 35.6892523,
        "lng": 51.3896004
      },
      "intensity": 65,
      "color": "#ff2d55",
      "url": "https://www.aljazeera.com/news/2026/5/23/iran-weighs-us-peace-proposal-despite-deep-and-significant-disagreements",
      "imageUrl": "https://www.aljazeera.com/wp-content/uploads/2026/05/afp_6a0f11f0c401-1779372528.jpg?resize=1920%2C1440"
    },
    {
      "id": 11,
      "headline": "Gas explosion at Chinese coal mine kills at least 90",
      "description": "President Xi Jinping has called on authorities nationwide to learn from the incident.",
      "mainLocation": {
        "name": "BEIJING, CHINA",
        "lat": 39.9057136,
        "lng": 116.3912972
      },
      "intensity": 45,
      "color": "#ff2d55",
      "url": "https://www.aljazeera.com/news/2026/5/23/gas-explosion-at-chinese-coal-mine-kills-at-least-90",
      "imageUrl": "https://www.aljazeera.com/wp-content/uploads/2020/08/782ce440b754409f89950c6f62ffa5ba_18.jpeg?resize=1200%2C675"
    }
  ]
}