{
  "date": "2026-07-19",
  "displayDate": "JUL 19, 2026",
  "bottomWord": "CONFRONTATION",
  "stories": [
    {
      "id": 2,
      "headline": "Laos says it cannot determine cause of  tourist deaths linked to methanol",
      "description": "Officials say they have no evidence of poisoning over the 2024 deaths because autopsies were not conducted.",
      "mainLocation": {
        "name": "VANG VIENG, LAOS",
        "lat": 18.9538961,
        "lng": 102.4563909
      },
      "intensity": 40,
      "color": "#ff6b35",
      "url": "https://www.bbc.co.uk/news/articles/cdx8rj99endo",
      "imageUrl": "https://ichef.bbci.co.uk/ace/branded_news/1200/cpsprodpb/dbc2/live/32672200-a8c8-11ef-a4fe-a3e9a6c5d640.jpg"
    },
    {
      "id": 3,
      "headline": "How the US and Iran dragged each other back toward war",
      "description": "Rising hostilities between the US and Iran threaten to drag both nations back to war.",
      "mainLocation": {
        "name": "WASHINGTON, D.C., UNITED STATES",
        "lat": 38.8950982,
        "lng": -77.0363849
      },
      "intensity": 80,
      "color": "#ffb800",
      "url": "https://apnews.com/article/iran-us-war-escalation-shipping-strait-hormuz-179973cfe1fb3fa1b7ea7b816648ad9c",
      "imageUrl": "https://dims.apnews.com/dims4/default/aa7ac3b/2147483647/strip/true/crop/8371x5578+0+2/resize/980x653!/quality/90/?url=https%3A%2F%2Fassets.apnews.com%2Fb8%2Fb2%2Fe837e8e9b350ab2e7fb73d71e24d%2F5a20d04b0d874fdc82b6dfe7c4c3163c"
    },
    {
      "id": 5,
      "headline": "7 killed and more than 50 wounded in Ukrainian drone attack on Russian regions",
      "description": "Ukrainian drone attacks overnight killed seven people and wounded 51 in Russia.",
      "mainLocation": {
        "name": "KYIV, UKRAINE",
        "lat": 50.4500336,
        "lng": 30.5241361
      },
      "intensity": 50,
      "color": "#5ac8fa",
      "url": "https://apnews.com/article/russia-ukraine-war-drone-attacks-c2d0d713643288b81dbbea714d5db5ac",
      "imageUrl": "https://dims.apnews.com/dims4/default/295c329/2147483647/strip/true/crop/675x450+12+0/resize/980x653!/quality/90/?url=https%3A%2F%2Fassets.apnews.com%2F90%2F29%2F4e3c1cc7446089a9101a7bdff4c8%2Fdefaultshareimage-copy.png"
    },
    {
      "id": 8,
      "headline": "Burnham to announce plans for new North Sea oil and gas drilling",
      "description": "Burnham's plans clash with Labour’s manifesto pledge to halt new drilling licenses.",
      "mainLocation": {
        "name": "LONDON, UNITED KINGDOM",
        "lat": 51.5074456,
        "lng": -0.1277653
      },
      "intensity": 45,
      "color": "#ffb800",
      "url": "https://www.bbc.co.uk/news/articles/c935yx2z9d4o",
      "imageUrl": "https://ichef.bbci.co.uk/ace/branded_news/1200/cpsprodpb/a30c/live/c032d1a0-8270-11f1-b976-0b9c15b0ccfc.jpg"
    },
    {
      "id": 9,
      "headline": "US and Iran exchange strikes as they struggle over Strait of Hormuz",
      "description": "The US and Iran exchange strikes as the battle over the Strait of Hormuz intensifies.",
      "mainLocation": {
        "name": "TEHRAN, IRAN",
        "lat": 35.6892523,
        "lng": 51.3896004
      },
      "intensity": 85,
      "color": "#34c759",
      "url": "https://apnews.com/article/iran-us-hormuz-strait-war-july-18-2026-5adfef67554652580963684d9a663af2",
      "imageUrl": "https://dims.apnews.com/dims4/default/295c329/2147483647/strip/true/crop/675x450+12+0/resize/980x653!/quality/90/?url=https%3A%2F%2Fassets.apnews.com%2F90%2F29%2F4e3c1cc7446089a9101a7bdff4c8%2Fdefaultshareimage-copy.png"
    }
  ]
}